LICENSE
setup.py
resources/config/config
resources/fonts/FreeUniversal-Bold.ttf
resources/fonts/FreeUniversal-BoldItalic.ttf
resources/fonts/FreeUniversal-Italic.ttf
resources/fonts/FreeUniversal-Regular.ttf
resources/images/logo.icns
resources/images/logo.png
resources/images/nest selected.png
resources/images/nest unselected.png
resources/images/node selected.png
resources/images/node unselected.png
resources/images/ps selected.png
resources/images/ps unselected.png
resources/library/load list values from files_fc6175d6-c18b-4403-9b79-bd2b0b0012ff.pomset
resources/library/loadLibraryDefinition.pomset
resources/library/loadLibraryDefinitions.pomset
resources/library/word count reducer_08979d5f-6c0d-43b7-9206-dfe69eae6c26.pomset
resources/library/word count_8613fe86-e7fc-4487-b4d2-0989706f8825.pomset
resources/licenses/commercial.txt
resources/licenses/gpl-2.0.txt
resources/licenses/gpl-3.0.txt
resources/qt/cloud pool dialog.ui
resources/qt/edit definition dialog.ui
resources/qt/edit parameter binding dialog.ui
resources/qt/edit parameter dialog.ui
resources/qt/edit parameter sweep group.ui
resources/qt/edit python parameter dialog.ui
resources/qt/edit task dialog.ui
resources/qt/euca2ools configuration dialog.ui
resources/qt/hadoop configuration dialog.ui
resources/qt/license agreement.ui
resources/qt/python configuration dialog.ui
resources/qt/select definition dialog.ui
resources/qt/task output dialog.ui
resources/qt/task preview dialog.ui
resources/testdata/TestLayoutPolicy/TestGraphvizLayoutPolicy/config
resources/wx/fbp/configuration frame.fbp
resources/wx/fbp/create definition.fbp
resources/wx/fbp/definition list dialog.fbp
resources/wx/fbp/edit definition dialog.fbp
resources/wx/fbp/edit parameter dialog.fbp
resources/wx/fbp/edit task dialog.fbp
resources/wx/fbp/euca2ools dialog.fbp
resources/wx/fbp/execution preview.fbp
resources/wx/fbp/fold panels.fbp
resources/wx/fbp/hadoop dialog.fbp
resources/wx/fbp/parameter values dialog.fbp
src/pomsets_gui.egg-info/PKG-INFO
src/pomsets_gui.egg-info/SOURCES.txt
src/pomsets_gui.egg-info/dependency_links.txt
src/pomsets_gui.egg-info/requires.txt
src/pomsets_gui.egg-info/top_level.txt
